Metadata-Version: 1.1
Name: elevationapi
Version: 1.0.3
Summary: Get the elevation of any land point on Earth using elevationapi.xyz
Home-page: https://github.com/Frankkkkk/python-elevationapi
Author: Frank Villaro-Dixon
Author-email: frank@villaro-dixon.eu
License: UNKNOWN
Keywords: elevation altitude earth elevationapi.xyz
Platform: UNKNOWN
Classifier: Topic :: Scientific/Engineering :: Atmospheric Science
Classifier: Topic :: Scientific/Engineering :: GIS
Classifier: License :: OSI Approved :: MIT License
Classifier: Programming Language :: Python :: 3
Classifier: Programming Language :: Python :: 3.2
Classifier: Programming Language :: Python :: 3.3
Classifier: Programming Language :: Python :: 3.4
Classifier: Programming Language :: Python :: 3.5
